ds_ml_data_kit/__init__.py
ds_ml_data_kit/functions.py
ds_ml_data_kit-0.1.dist-info/METADATA
ds_ml_data_kit-0.1.dist-info/WHEEL
ds_ml_data_kit-0.1.dist-info/top_level.txt
ds_ml_data_kit-0.1.dist-info/RECORD
